doc_spell/.doc-spell.yml
doc_spell/__init__.py
doc_spell/__main__.py
doc_spell/conf.py
doc_spell/cspell.py
doc_spell/formatters.py
doc_spell/__version__.py
doc_spell-0.2.0.dist-info/entry_points.txt
doc_spell-0.2.0.dist-info/WHEEL
doc_spell-0.2.0.dist-info/METADATA
doc_spell-0.2.0.dist-info/licenses/LICENSE
doc_spell-0.2.0.dist-info/RECORD
