Metadata-Version: 2.1
Name: doc-spell
Version: 0.2.0
Summary: code documentation spell checker
Author-email: Anatoly Asviyan <aanatoly@gmail.com>
Classifier: Development Status :: 4 - Beta
Classifier: Environment :: Console
Classifier: Intended Audience :: Developers
Classifier: License :: OSI Approved :: MIT License
Classifier: Operating System :: POSIX
Classifier: Programming Language :: Python :: 3
Classifier: Topic :: Software Development
Requires-Dist: identify
Requires-Dist: pyaml
Requires-Dist: pydevkit<4.0.0,>=3.1.2
Requires-Dist: pygments
Requires-Dist: schema
Project-URL: Homepage, https://github.com/aanatoly/doc-spell
Project-URL: Repository, https://github.com/aanatoly/doc-spell
